{"clientes":[{"id":"1","nombre":"Zunfeld Digital"},{"id":"5","nombre":"Pepsi"}],"actividades":[{"cliente":"Zunfeld Digital","sucursal":"observatorio","proyecto":"proyecto","tareas":[{"id_Bitacora":"16","id_Actividad":"16","Actividad":"abc","Observaciones":"abc"}]},{"cliente":"Zunfeld Digital","sucursal":"observatorio","proyecto":"proyecto","tareas":[{"id_Bitacora":"17","id_Actividad":"17","Actividad":"17 uno","Observaciones":""}]},{"cliente":"Zunfeld Digital","sucursal":"observatorio","proyecto":"proyecto","tareas":[{"id_Bitacora":"18","id_Actividad":"18","Actividad":"omi","Observaciones":"omi"},{"id_Bitacora":"18","id_Actividad":"18","Actividad":"abc","Observaciones":"abc"}]},{"cliente":"Zunfeld Digital","sucursal":"observatorio","proyecto":"proyecto","tareas":[{"id_Bitacora":"19","id_Actividad":"19","Actividad":"","Observaciones":""},{"id_Bitacora":"19","id_Actividad":"19","Actividad":" modem","Observaciones":"remplazar  modem"},{"id_Bitacora":"19","id_Actividad":"19","Actividad":"chisto","Observaciones":"revizar"}]},{"cliente":"Zunfeld Digital","sucursal":"observatorio","proyecto":"proyecto","tareas":[{"id_Bitacora":"20","id_Actividad":"20","Actividad":"webos a todos","Observaciones":"en especial al omar"}]},{"cliente":"Zunfeld Digital","sucursal":"observatorio","proyecto":"proyecto","tareas":[{"id_Bitacora":"21","id_Actividad":"21","Actividad":"cuatro","Observaciones":"asdasd"},{"id_Bitacora":"21","id_Actividad":"21","Actividad":"tres","Observaciones":"asdasdasd"},{"id_Bitacora":"21","id_Actividad":"21","Actividad":"dos","Observaciones":"asdasd"},{"id_Bitacora":"21","id_Actividad":"21","Actividad":"uno","Observaciones":"asdasdasd"}]},{"cliente":"Pepsi","sucursal":"DEMO01","proyecto":"01","tareas":[{"id_Bitacora":"22","id_Actividad":"22","Actividad":"AC01","Observaciones":"AC01"}]}]}